picknpull/__init__.py
picknpull/picknpull.py
picknpull-0.1.2.dist-info/LICENSE
picknpull-0.1.2.dist-info/METADATA
picknpull-0.1.2.dist-info/WHEEL
picknpull-0.1.2.dist-info/top_level.txt
picknpull-0.1.2.dist-info/RECORD
