Metadata-Version: 2.1
Name: picknpull
Version: 0.1.2
Summary: An automated search for the Pick N Pull website.
Home-page: https://bitbucket.org/jscheiber22/pick-n-pull-automated-search/src/
Author: James Scheiber
Author-email: jscheiber22@gmail.com
License: UNKNOWN
Platform: UNKNOWN
Classifier: Programming Language :: Python :: 3
Classifier: License :: OSI Approved :: MIT License
Classifier: Operating System :: OS Independent
Requires-Python: >=3.6
Requires-Dist: selenium
Requires-Dist: webdriver-manager
